octobot_services/__init__.pxd
octobot_services/__init__.py
octobot_services/abstract_service_user.py
octobot_services/constants.py
octobot_services/enums.py
octobot_services/errors.py
octobot_services/octobot_channel_consumer.py
octobot_services/api/__init__.py
octobot_services/api/interfaces.py
octobot_services/api/notification.py
octobot_services/api/service_feeds.py
octobot_services/api/services.py
octobot_services/channel/__init__.py
octobot_services/channel/abstract_service_feed.py
octobot_services/channel/notifications.py
octobot_services/channel/user_commands.py
octobot_services/interfaces/__init__.py
octobot_services/interfaces/abstract_interface.py
octobot_services/interfaces/interface_factory.py
octobot_services/interfaces/bots/__init__.py
octobot_services/interfaces/bots/abstract_bot_interface.py
octobot_services/interfaces/util/__init__.py
octobot_services/interfaces/util/bot.py
octobot_services/interfaces/util/order.py
octobot_services/interfaces/util/portfolio.py
octobot_services/interfaces/util/position.py
octobot_services/interfaces/util/profitability.py
octobot_services/interfaces/util/trader.py
octobot_services/interfaces/util/util.py
octobot_services/interfaces/web/__init__.py
octobot_services/interfaces/web/abstract_web_interface.py
octobot_services/managers/__init__.py
octobot_services/managers/interface_manager.py
octobot_services/managers/service_feed_manager.py
octobot_services/managers/service_manager.py
octobot_services/notification/__init__.py
octobot_services/notification/formated_notifications.py
octobot_services/notification/notification.py
octobot_services/notifier/__init__.py
octobot_services/notifier/abstract_notifier.py
octobot_services/notifier/notifier_factory.py
octobot_services/service_feeds/__init__.py
octobot_services/service_feeds/abstract_service_feed.py
octobot_services/service_feeds/service_feed_exception.py
octobot_services/service_feeds/service_feed_factory.py
octobot_services/service_feeds/service_feeds.py
OctoBot_Services-1.5.6.dist-info/LICENSE
OctoBot_Services-1.5.6.dist-info/METADATA
OctoBot_Services-1.5.6.dist-info/WHEEL
OctoBot_Services-1.5.6.dist-info/top_level.txt
OctoBot_Services-1.5.6.dist-info/RECORD
