Metadata-Version: 2.1
Name: OctoBot-Services
Version: 1.5.6
Summary: OctoBot project services package
Home-page: https://github.com/Drakkar-Software/OctoBot-Services
Author: Drakkar-Software
Author-email: drakkar-software@protonmail.com
License: LGPL-3.0
Classifier: Development Status :: 5 - Production/Stable
Classifier: Operating System :: OS Independent
Classifier: Operating System :: MacOS :: MacOS X
Classifier: Operating System :: Microsoft :: Windows
Classifier: Operating System :: POSIX
Classifier: Programming Language :: Python :: 3.8
Classifier: Programming Language :: Python :: 3.9
Requires-Python: >=3.8
License-File: LICENSE
Requires-Dist: Async-Channel (<2.2,>=2.1)
Requires-Dist: OctoBot-Commons (<1.9,>=1.8)
Requires-Dist: OctoBot-Trading (<2.4,>=2.3.0)
Requires-Dist: asyncpraw (==7.7.0)
Requires-Dist: python-telegram-bot (==20.2)
Requires-Dist: telethon (==1.24.0)
Requires-Dist: simplifiedpytrends (>=1.1.2)
Requires-Dist: pyngrok (==6.0.0)
Requires-Dist: openai (==0.27.6)
Requires-Dist: flask (==2.3.2)
Requires-Dist: jinja2 (>=3.1.2)
Requires-Dist: flask-compress (==1.13)
Requires-Dist: flask-caching (==2.0.2)
Requires-Dist: flask-login (==0.6.2)
Requires-Dist: flask-cors (==3.0.10)
Requires-Dist: WTForms (==3.0.1)
Requires-Dist: Flask-WTF (==1.1.1)
Requires-Dist: gevent (==22.10.2)
Requires-Dist: gevent-websocket (==0.10.1)
Requires-Dist: flask-socketio (==5.3.3)
Requires-Dist: newspaper3k (==0.2.8)
Requires-Dist: vaderSentiment (==3.3.2)
